{
	"instance" : {
		"handleError:" : "FrancoisStephany 12/15/2011 18:55",
		"defaultApiUrl" : "FrancoisStephany 12/15/2011 18:42",
		"apiKey" : "FrancoisStephany 12/15/2011 17:38",
		"processIncorrectFields:" : "FrancoisStephany 12/15/2011 18:53",
		"buildZnClientForContent:" : "FrancoisStephany 12/15/2011 18:12",
		"developmentMode" : "FrancoisStephany 12/15/2011 18:14",
		"debugStream" : "FrancoisStephany 12/15/2011 18:14",
		"apiKey:" : "FrancoisStephany 12/15/2011 17:22",
		"handleResponse:" : "FrancoisStephany 12/15/2011 18:54",
		"send:" : "FrancoisStephany 12/26/2011 16:35",
		"defaultApiKey" : "FrancoisStephany 12/15/2011 17:40",
		"apiUrl" : "FrancoisStephany 12/15/2011 17:39",
		"simulateSendOf:" : "FrancoisStephany 12/20/2011 15:52",
		"debugStream:" : "FrancoisStephany 12/15/2011 18:28"
	},
	"class" : { }
}